{
  "type": "minecraft:crafting_shaped",
  "group": "spartanweaponry:boomerang",
  "pattern": [
    "IWW",
    "W  ",
    "W  "
  ],
  "key": {
    "I": {
      "tag": "forge:ingots/aluminium"
    },
    "W": {
      "tag": "minecraft:planks"
    }
  },
  "result": {
    "item": "spartanextramaterial:boomerang_aluminium"
  },
  "conditions": [
    {
      "disabled": [
        "boomerang",
        "aluminium"
      ],
      "type": "spartanweaponry:type_disabled"
    },
    {
      "value": {
        "tag": "forge:ingots/aluminium",
        "type": "forge:tag_empty"
      },
      "type": "forge:not"
    }
  ]
}